{
  "backend": "synthetic_cmodel",
  "entries": [
    {
      "cycle": 1000,
      "experiment_id": "t01-vrgather-vv-m4",
      "marker": "before",
      "pc": "0x80000000"
    },
    {
      "cycle": 1013,
      "experiment_id": "t01-vrgather-vv-m4",
      "marker": "after",
      "pc": "0x80000004"
    },
    {
      "cycle": 1013,
      "experiment_id": "t01-vrgather-vv-m4",
      "marker": "program_end",
      "pc": "0x80000008"
    }
  ],
  "experiment_id": "t01-vrgather-vv-m4",
  "instruction_id": "vrgather_vv",
  "lmul": "m4",
  "marker_baseline_cycles": 0,
  "mode": "synthetic_calibration",
  "result_group": "common",
  "scaffold": false,
  "schema_version": 1,
  "synthetic": {
    "backend": "synthetic_cmodel",
    "configured": {
      "latency_base": 5,
      "latency_lmul_k": 2,
      "pipe": "pipe1",
      "release_base": 1,
      "release_lmul_k": 1
    },
    "instruction_id": "vrgather_vv",
    "latency_cycles": 13,
    "lmul": "m4",
    "measured_delta_cycles": 13,
    "pipe": "pipe1",
    "release_cycles": 5,
    "timing_model": "config/rvv_timing_model.yaml",
    "timing_model_entry_found": true,
    "timing_model_mode": "synthetic_ground_truth"
  },
  "template_id": "T01_DECODE_EXEC_KILLCHECK"
}
